factscore/__init__.py
factscore/abstain_detection.py
factscore/atomic_facts.py
factscore/clm.py
factscore/download_data.py
factscore/factscorer.py
factscore/lm.py
factscore/npm.py
factscore/openai_lm.py
factscore/retrieval.py
factscore/utils.py
factscore-0.2.0.dist-info/LICENSE
factscore-0.2.0.dist-info/METADATA
factscore-0.2.0.dist-info/WHEEL
factscore-0.2.0.dist-info/RECORD
