Metadata-Version: 2.1
Name: factscore
Version: 0.2.0
Summary: FactScore is an automatic evaluation metric for factual precision in long-form text generation. It uses large language models and retrieval to break down generations into atomic facts and then measure the correctness with respect to a knowledge source (like Wikipedia).
License: MIT
Author: Sewon Min
Author-email: sewon@cs.washington.edu
Requires-Python: >=3.7.1,<4.0.0
Classifier: License :: OSI Approved :: MIT License
Classifier: Programming Language :: Python :: 3
Classifier: Programming Language :: Python :: 3.8
Classifier: Programming Language :: Python :: 3.9
Classifier: Programming Language :: Python :: 3.10
Classifier: Programming Language :: Python :: 3.11
Requires-Dist: nltk (>=3.8.1,<4.0.0)
Requires-Dist: openai (>=0.27.7,<0.28.0)
Requires-Dist: pysqlite-binary (>=0.5.0,<0.6.0)
Requires-Dist: rank-bm25 (>=0.2.2,<0.3.0)
Requires-Dist: sentence-transformers (>=2.2.2,<3.0.0)
Requires-Dist: spacy (>=3.5.3,<4.0.0)
Requires-Dist: torch (>=1.13.0,<2.0.0)
Requires-Dist: transformers (>=4.29.2,<5.0.0)
